<?xml version='1.0' encoding='UTF-8'?>
<nfe>
<DataEmissao>03/07/2023</DataEmissao>
<NotaFiscal>18587</NotaFiscal>
<Warehouse>WHPOA</Warehouse>
<CidadeOrigem>Porto Alegre</CidadeOrigem>
<CidadeDestino>Campo Grande</CidadeDestino>
<CodCliente>66435</CodCliente>
<TotalNotaFiscal>409,84</TotalNotaFiscal>
<Volumes>1</Volumes>
<PesoBruto>0,702</PesoBruto>
<CodTransportadora>960019</CodTransportadora>
<Transportadora>Minaspress</Transportadora>
<CentroDistribuicao>Belo Horizonte</CentroDistribuicao>
<TipoTransporte>Convencional</TipoTransporte>
<PrazoContratado>11</PrazoContratado>
<DataColeta>03/07/2023</DataColeta>
<DataEntrega>09/07/2023</DataEntrega>
<Ocorrencia>Nenhuma</Ocorrencia>
</nfe>
