<?xml version='1.0' encoding='UTF-8'?>
<nfe>
<DataEmissao>08/07/2023</DataEmissao>
<NotaFiscal>18591</NotaFiscal>
<Warehouse>WHSJC</Warehouse>
<CidadeOrigem>Sao Jose dos Campos</CidadeOrigem>
<CidadeDestino>Sao Paulo</CidadeDestino>
<CodCliente>66349</CodCliente>
<TotalNotaFiscal>8512,3</TotalNotaFiscal>
<Volumes>2</Volumes>
<PesoBruto>34,052</PesoBruto>
<CodTransportadora>960019</CodTransportadora>
<Transportadora>Minaspress</Transportadora>
<CentroDistribuicao>Belo Horizonte</CentroDistribuicao>
<TipoTransporte>Convencional</TipoTransporte>
<PrazoContratado>6</PrazoContratado>
<DataColeta>08/07/2023</DataColeta>
<DataEntrega>12/07/2023</DataEntrega>
<Ocorrencia>Nenhuma</Ocorrencia>
</nfe>
