<?xml version='1.0' encoding='UTF-8'?>
<nfe>
<DataEmissao>15/07/2023</DataEmissao>
<NotaFiscal>18618</NotaFiscal>
<Warehouse>WHBHZ</Warehouse>
<CidadeOrigem>Belo Horizonte</CidadeOrigem>
<CidadeDestino>Belo Horizonte</CidadeDestino>
<CodCliente>66359</CodCliente>
<TotalNotaFiscal>97,21</TotalNotaFiscal>
<Volumes>1</Volumes>
<PesoBruto>1,9</PesoBruto>
<CodTransportadora>960019</CodTransportadora>
<Transportadora>Minaspress</Transportadora>
<CentroDistribuicao>Belo Horizonte</CentroDistribuicao>
<TipoTransporte>Convencional</TipoTransporte>
<PrazoContratado>11</PrazoContratado>
<DataColeta>15/07/2023</DataColeta>
<DataEntrega>21/07/2023</DataEntrega>
<Ocorrencia>Nenhuma</Ocorrencia>
</nfe>
