<?xml version='1.0' encoding='UTF-8'?>
<nfe>
<DataEmissao>21/07/2023</DataEmissao>
<NotaFiscal>18641</NotaFiscal>
<Warehouse>WHVIX</Warehouse>
<CidadeOrigem>Vitoria</CidadeOrigem>
<CidadeDestino>Sao Paulo</CidadeDestino>
<CodCliente>66421</CodCliente>
<TotalNotaFiscal>238,75</TotalNotaFiscal>
<Volumes>1</Volumes>
<PesoBruto>0,2</PesoBruto>
<CodTransportadora>960019</CodTransportadora>
<Transportadora>Minaspress</Transportadora>
<CentroDistribuicao>Belo Horizonte</CentroDistribuicao>
<TipoTransporte>Convencional</TipoTransporte>
<PrazoContratado>4</PrazoContratado>
<DataColeta>22/07/2023</DataColeta>
<DataEntrega>28/07/2023</DataEntrega>
<Ocorrencia>Nenhuma</Ocorrencia>
</nfe>
