<?xml version='1.0' encoding='UTF-8'?>
<nfe>
<DataEmissao>18/09/2021</DataEmissao>
<NotaFiscal>16113</NotaFiscal>
<Warehouse>WHRIO</Warehouse>
<CidadeOrigem>Rio De Janeiro</CidadeOrigem>
<CidadeDestino>Manaus</CidadeDestino>
<CodCliente>66247</CodCliente>
<TotalNotaFiscal>707,65</TotalNotaFiscal>
<Volumes>1</Volumes>
<PesoBruto>3,8</PesoBruto>
<CodTransportadora>960019</CodTransportadora>
<Transportadora>Minaspress</Transportadora>
<CentroDistribuicao>Belo Horizonte</CentroDistribuicao>
<TipoTransporte>Convencional</TipoTransporte>
<PrazoContratado>1</PrazoContratado>
<DataColeta>19/09/2021</DataColeta>
<DataEntrega>24/09/2021</DataEntrega>
<Ocorrencia>Nenhuma</Ocorrencia>
</nfe>
