<?xml version='1.0' encoding='UTF-8'?>
<nfe>
<DataEmissao>26/10/2021</DataEmissao>
<NotaFiscal>16252</NotaFiscal>
<Warehouse>WHPOA</Warehouse>
<CidadeOrigem>Porto Alegre</CidadeOrigem>
<CidadeDestino>Goiania</CidadeDestino>
<CodCliente>66232</CodCliente>
<TotalNotaFiscal>401,89</TotalNotaFiscal>
<Volumes>1</Volumes>
<PesoBruto>0,75</PesoBruto>
<CodTransportadora>960019</CodTransportadora>
<Transportadora>Minaspress</Transportadora>
<CentroDistribuicao>Belo Horizonte</CentroDistribuicao>
<TipoTransporte>Convencional</TipoTransporte>
<PrazoContratado>7</PrazoContratado>
<DataColeta>26/10/2021</DataColeta>
<DataEntrega>02/11/2021</DataEntrega>
<Ocorrencia>Nenhuma</Ocorrencia>
</nfe>
